{
  "id": "getting-started/setup-first-herd",
  "title": "Set Up Your First Herd",
  "description": "Herds keep animals grouped by farm, project, species, pasture, barn, class, or any structure that fits your workflow.",
  "source": "@site/docs/getting-started/setup-first-herd.md",
  "sourceDirName": "getting-started",
  "slug": "/getting-started/setup-first-herd",
  "permalink": "/getting-started/setup-first-herd",
  "draft": false,
  "unlisted": false,
  "tags": [],
  "version": "current",
  "frontMatter": {
    "title": "Set Up Your First Herd"
  },
  "sidebar": "tutorialSidebar",
  "previous": {
    "title": "Dashboard Tour",
    "permalink": "/getting-started/dashboard-tour"
  },
  "next": {
    "title": "Add Your First Animal",
    "permalink": "/getting-started/add-first-animal"
  }
}